MANIFEST.in
README.rst
setup.py
docs/HISTORY.txt
src/mobi/__init__.py
src/mobi.devices.egg-info/PKG-INFO
src/mobi.devices.egg-info/SOURCES.txt
src/mobi.devices.egg-info/dependency_links.txt
src/mobi.devices.egg-info/entry_points.txt
src/mobi.devices.egg-info/namespace_packages.txt
src/mobi.devices.egg-info/not-zip-safe
src/mobi.devices.egg-info/requires.txt
src/mobi.devices.egg-info/top_level.txt
src/mobi/devices/__init__.py
src/mobi/devices/classifiers.py
src/mobi/devices/configure.zcml
src/mobi/devices/device.py
src/mobi/devices/data/Infrae/device_user_agent_patterns.json
src/mobi/devices/data/MIT/device_user_agent_patterns.json
src/mobi/devices/data/MIT/platforms.json
src/mobi/devices/data/WURFL/wurfl.xml.gz
src/mobi/devices/index/__init__.py
src/mobi/devices/index/radixtree.py
src/mobi/devices/index/tcdbm.py
src/mobi/devices/tests/__init__.py
src/mobi/devices/tests/test_doctest_device_detection.py
src/mobi/devices/tests/test_doctest_index.py
src/mobi/devices/tests/test_doctest_router.py
src/mobi/devices/tests/test_doctest_wurfl_parsing.py
src/mobi/devices/wsgi/__init__.py
src/mobi/devices/wsgi/devicedetection.py
src/mobi/devices/wsgi/router.py
src/mobi/devices/wurfl/__init__.py
src/mobi/devices/wurfl/db.py
src/mobi/devices/wurfl/parser.py
src/mobi/devices/wurfl/platforms.py