Metadata-Version: 1.0
Name: mobi.devices
Version: 1.1
Summary: Mobile Device detection library and wsgi middlewares
Home-page: http://mobi.infrae.com/
Author: Antonin Amand at Infrae
Author-email: info@infrae.com
License: BSD
Platform: UNKNOWN
